make_action/__init__.py
make_action/main.py
make_action-1.0.2.dist-info/METADATA
make_action-1.0.2.dist-info/WHEEL
make_action-1.0.2.dist-info/entry_points.txt
make_action-1.0.2.dist-info/top_level.txt
make_action-1.0.2.dist-info/RECORD
