Metadata-Version: 2.2
Name: make_action
Version: 1.0.2
Summary: Un package Python CLI
Author: Mangozmorgan
Project-URL: homepage, https://github.com/votre_nom/my_package
Requires-Python: >=3.6
Requires-Dist: click
Requires-Dist: pyyaml
Requires-Dist: ruamel.yaml
